{
  "users": [
    {
      "id": "bZ_HmBQ5b",
      "firstName": "John",
      "lastName": "Doe",
      "email": "john@example.com"
    },
    {
      "id": "Ln37fsDP1S",
      "firstName": "Mary",
      "lastName": "Moe",
      "email": "mary@example.com"
    },
    {
      "id": "uLhWf1RLAv",
      "firstName": "July",
      "lastName": "Dooley",
      "email": "july@example.com"
    },
    {
      "id": "Ha7WiyqMgp",
      "firstName": "Tay",
      "lastName": "Nguyen",
      "email": "tay@example.com"
    },
    {
      "firstName": "Han",
      "lastName": "Lam",
      "email": "han@example.com",
      "id": "3Y-n6QaQQ"
    },
    {
      "firstName": "Linh",
      "lastName": "Ly",
      "email": "linh@example.com",
      "id": "eCOqg4jYy"
    },
    {
      "firstName": "Nam",
      "lastName": "Dinh",
      "email": "nam@example.com",
      "id": "atAU6GLoR"
    }
  ]
}